dextra/__init__.py
dextra/base.py
dextra/extractor_factory.py
dextra/integration.py
dextra/ml_extractor.py
dextra/regex_extractor.py
dextra-0.1.1.dist-info/LICENSE
dextra-0.1.1.dist-info/METADATA
dextra-0.1.1.dist-info/WHEEL
dextra-0.1.1.dist-info/RECORD
